psion/__init__.py
psion/jose/__init__.py
psion/jose/exceptions.py
psion/jose/jwa/__init__.py
psion/jose/jwa/jwk.py
psion/jose/jwa/jws.py
psion/jose/jwk.py
psion/jose/jws.py
psion/jose/jwt.py
psion/oauth2/__init__.py
psion/oauth2/adapter.py
psion/oauth2/authentication/__init__.py
psion/oauth2/authentication/client_authentication.py
psion/oauth2/authentication/methods/__init__.py
psion/oauth2/authentication/methods/base.py
psion/oauth2/authentication/methods/client_secret_basic.py
psion/oauth2/authentication/methods/client_secret_post.py
psion/oauth2/authentication/methods/none.py
psion/oauth2/config.py
psion/oauth2/endpoints/__init__.py
psion/oauth2/endpoints/authorization.py
psion/oauth2/endpoints/base.py
psion/oauth2/endpoints/revocation.py
psion/oauth2/endpoints/token.py
psion/oauth2/exceptions.py
psion/oauth2/grants/__init__.py
psion/oauth2/grants/authorization_code.py
psion/oauth2/grants/base.py
psion/oauth2/grants/client_credentials.py
psion/oauth2/grants/refresh_token.py
psion/oauth2/mixins.py
psion/oauth2/models/__init__.py
psion/oauth2/models/http.py
psion/oauth2/models/scopes.py
psion/oauth2/providers/__init__.py
psion/oauth2/providers/base.py
psion/oauth2/providers/starlette.py
psion/oidc/__init__.py
psion/oidc/claims.py
psion/oidc/flows/__init__.py
psion/oidc/flows/authorization_code.py
psion/webtools.py
psion-0.1.4.dist-info/LICENSE
psion-0.1.4.dist-info/WHEEL
psion-0.1.4.dist-info/METADATA
psion-0.1.4.dist-info/RECORD
