Metadata-Version: 2.1
Name: psion
Version: 0.1.4
Summary: Asynchronous WebAuth library for python.
Home-page: https://github.com/revensky/psion
License: MIT
Keywords: JOSE,OAuth 2.1,OpenID Connect
Author: Eduardo Ribeiro Rezende
Author-email: eduardorbr7@gmail.com
Requires-Python: >=3.9,<4.0
Classifier: Development Status :: 3 - Alpha
Classifier: Environment :: Web Environment
Classifier: Framework :: AsyncIO
Classifier: Intended Audience :: Developers
Classifier: License :: OSI Approved :: MIT License
Classifier: Operating System :: OS Independent
Classifier: Programming Language :: Python :: 3
Classifier: Programming Language :: Python :: 3.8
Classifier: Programming Language :: Python :: 3.9
Classifier: Topic :: Software Development :: Libraries :: Application Frameworks
Classifier: Typing :: Typed
Requires-Dist: cryptography (>=3.3.1,<4.0.0)
Project-URL: Repository, https://github.com/revensky/psion.git
